tests/TestDate.py
tests/TestDecimal.py
tests/__init__.py
yhq_pyhelper/__init__.py
yhq_pyhelper/date.py
yhq_pyhelper/decimalUtils.py
yhq_pyhelper/http.py
yhq_pyhelper/mysql.py
yhq_Pyhelper-0.1.3.dist-info/LICENSE
yhq_Pyhelper-0.1.3.dist-info/METADATA
yhq_Pyhelper-0.1.3.dist-info/WHEEL
yhq_Pyhelper-0.1.3.dist-info/top_level.txt
yhq_Pyhelper-0.1.3.dist-info/RECORD
